pyION/__init__.py
pyION/__main__.py
pyION/cache.py
pyION/main.py
pyION/manager.py
pyION/models.py
pyION/settings.py
pyION/worker.py
ion_http_api-0.0.0.dist-info/METADATA
ion_http_api-0.0.0.dist-info/WHEEL
ion_http_api-0.0.0.dist-info/entry_points.txt
ion_http_api-0.0.0.dist-info/top_level.txt
ion_http_api-0.0.0.dist-info/zip-safe
ion_http_api-0.0.0.dist-info/RECORD
