Metadata-Version: 2.2
Name: ion-http-api
Version: 0.0.0
Summary: HTTP API for ION (Ice Open Network)
Home-page: https://github.com/ice-blockchain/ion-http-api
Author: K-Dimentional Tree
Author-email: kdimentionaltree@gmail.com
Classifier: Development Status :: 3 - Alpha
Classifier: Intended Audience :: Developers
Classifier: Programming Language :: Python :: 3.9
Classifier: Programming Language :: Python :: 3.10
Classifier: Programming Language :: Python :: 3.11
Classifier: Programming Language :: Python :: 3.12
Classifier: License :: Other/Proprietary License
Classifier: Topic :: Software Development :: Libraries
Requires-Python: >=3.9
Requires-Dist: redis==5.0.1
Requires-Dist: loguru==0.6.0
Requires-Dist: fastapi==0.99.1
Requires-Dist: pydantic==1.10.14
Requires-Dist: requests==2.28.0
Requires-Dist: ring==0.10.1
Requires-Dist: uvicorn==0.17.6
Requires-Dist: gunicorn==20.1.0
Requires-Dist: pytonlib==0.0.64
Requires-Dist: inject==4.3.1
Dynamic: author
Dynamic: author-email
Dynamic: classifier
Dynamic: description
Dynamic: description-content-type
Dynamic: home-page
Dynamic: requires-dist
Dynamic: requires-python
Dynamic: summary
